pylookyloomonitoring/__init__.py
pylookyloomonitoring/api.py
pylookyloomonitoring/py.typed
pylookyloomonitoring-1.2.0.dist-info/METADATA
pylookyloomonitoring-1.2.0.dist-info/WHEEL
pylookyloomonitoring-1.2.0.dist-info/entry_points.txt
pylookyloomonitoring-1.2.0.dist-info/licenses/LICENSE
pylookyloomonitoring-1.2.0.dist-info/RECORD
