Metadata-Version: 2.4
Name: pylookyloomonitoring
Version: 1.2.0
Summary: Python API to connect to lookyloo monitoring
License-Expression: BSD-3-Clause
License-File: LICENSE
Author: Raphaël Vinot
Author-email: raphael.vinot@circl.lu
Requires-Python: >=3.9.2
Classifier: Development Status :: 5 - Production/Stable
Classifier: Environment :: Console
Classifier: Intended Audience :: Information Technology
Classifier: Intended Audience :: Science/Research
Classifier: Intended Audience :: Telecommunications Industry
Classifier: License :: OSI Approved :: BSD License
Classifier: Operating System :: POSIX :: Linux
Classifier: Programming Language :: Python :: 3
Classifier: Programming Language :: Python :: 3.10
Classifier: Programming Language :: Python :: 3.11
Classifier: Programming Language :: Python :: 3.12
Classifier: Programming Language :: Python :: 3.13
Classifier: Programming Language :: Python :: 3.14
Classifier: Topic :: Internet
Classifier: Topic :: Security
Provides-Extra: docs
Requires-Dist: Sphinx (>=8.2.3) ; (python_version >= "3.11") and (extra == "docs")
Requires-Dist: dateparser (>=1.2.2)
Requires-Dist: requests (>=2.32.5)
Project-URL: Documentation, https://pylookyloomonitoring.readthedocs.io/en/latest/index.html
Project-URL: Repository, https://github.com/Lookyloo/PyLookylooMonitoring
